my_custom_greeter/__init__.py
my_custom_greeter/main.py
my_custom_greeter-0.1.4.dist-info/entry_points.txt
my_custom_greeter-0.1.4.dist-info/WHEEL
my_custom_greeter-0.1.4.dist-info/METADATA
my_custom_greeter-0.1.4.dist-info/RECORD
